nidf/__init__.py
nidf/__main__.py
nidf/nidf.py
nidf-0.0.9.dist-info/LICENSE
nidf-0.0.9.dist-info/METADATA
nidf-0.0.9.dist-info/WHEEL
nidf-0.0.9.dist-info/top_level.txt
nidf-0.0.9.dist-info/RECORD
