Metadata-Version: 2.1
Name: nidf
Version: 0.0.9
Summary: nidf
Home-page: https://github.com/PyWoody/nidf
Author: Samuel Woodward
Author-email: sam@woodward.fyi
Maintainer: Samuel Woodward
Maintainer-email: sam@woodward.fyi
License: MIT
Project-URL: Bug Tracker, https://github.com/PyWoody/nidf/issues
Platform: UNKNOWN
Classifier: Programming Language :: Python :: 3
Requires-Python: >= 3.7
License-File: LICENSE
